adarsh_distributions/Binomialdistribution.py
adarsh_distributions/Gaussiandistribution.py
adarsh_distributions/Generaldistribution.py
adarsh_distributions/__init__.py
adarsh_distributions-1.1.dist-info/METADATA
adarsh_distributions-1.1.dist-info/WHEEL
adarsh_distributions-1.1.dist-info/top_level.txt
adarsh_distributions-1.1.dist-info/RECORD
