Metadata-Version: 2.1
Name: adarsh-distributions
Version: 1.1
Summary: Gaussian distributions
Home-page: UNKNOWN
Author: Adarsh Ghimire
Author-email: UNKNOWN
License: UNKNOWN
Platform: UNKNOWN
